README.md
setup.py
ScriptUITool/Tools.py
ScriptUITool/__init__.py
ScriptUITool/__main__.py
ScriptUITool/gl.py
ScriptUITool/start_ui.py
ScriptUITool/ui_model.py
ScriptUITool.egg-info/PKG-INFO
ScriptUITool.egg-info/SOURCES.txt
ScriptUITool.egg-info/dependency_links.txt
ScriptUITool.egg-info/requires.txt
ScriptUITool.egg-info/top_level.txt