Metadata-Version: 2.1
Name: ScriptUITool
Version: 1.2.1
Summary: UNKNOWN
Home-page: UNKNOWN
Author: 孙亮
License: UNKNOWN
Platform: UNKNOWN
